api/__init__.py
api/apiclient.py
api/card.py
api/deck.py
api/drawncards.py
api/fetchcache.py
test/__init__.py
test/test.py
boostrapsdk-0.0.12.dist-info/LICENSE
boostrapsdk-0.0.12.dist-info/METADATA
boostrapsdk-0.0.12.dist-info/WHEEL
boostrapsdk-0.0.12.dist-info/top_level.txt
boostrapsdk-0.0.12.dist-info/RECORD
